[
  {
    "presenter_name": "Lily",
    "presenter_name": "Josh",
    "presenter_name": "Zaid",
    "presenter_name": "Kyle",
    "presenter_name": "Claire",
    "presenter_name": "Julia",
    "presenter_name": "Sam",
    "presenter_name": "Heath",
    "presenter_name": "Da'Veed",
    "presenter_name": "Reeti",
  },
  {
    "keywords": "Enterprise Architecture Program",
    "keywords": "Machine Learning",
    "keywords": "Fraud Detection",
    "keywords": "Penetration Testing",
    "keywords": "DevOps",
    "keywords": "DevSecOps",
    "keywords": "Empathic Services in Banking",
  },
  {
    "college": "Purdue University",
    "college": "University of Illinois",
    "college": "Indiana University",
    "college": "Stanford University",
    "college": "University of Georgia",
    "college": "Trine University",
  },
  {
    "level": "C1",
    "level": "C2",
    "level": "S1",
    "level": "M",
    "level": "SM",
    "level": "AD",
  },
  {
    "solution": "TC - Core",
    "solution": "TC - PSS",
    "solution": "TC - S&P",
    "solution": "IAFA - IA Process",
    "solution": "IAFA - IT Audit",
  },
]
